setup.cfg
setup.py
wtforms_ndb/__init__.py
wtforms_ndb/fields.py
wtforms_ndb/ndb.py
wtforms_ndb.egg-info/PKG-INFO
wtforms_ndb.egg-info/SOURCES.txt
wtforms_ndb.egg-info/dependency_links.txt
wtforms_ndb.egg-info/requires.txt
wtforms_ndb.egg-info/top_level.txt