Metadata-Version: 1.1
Name: wtforms-ndb
Version: 0.0.2
Summary: Wtforms mapper for Appengine's NDB library.
Home-page: http://github.com/xlevus/wtforms-ndb
Author: Chris Targett
Author-email: chris@xlevus.net
License: UNKNOWN
Keywords: wtforms appengine ndb
Platform: UNKNOWN
Classifier: Environment :: Web Environment
Classifier: Intended Audience :: Developers
Classifier: Programming Language :: Python :: 2.7
Classifier: Topic :: Internet :: WWW/HTTP :: Dynamic Content
Classifier: Topic :: Software Development :: Libraries :: Python Modules
